<?xml version="1.0" encoding="utf-8" ?>
<dwsync>
<file name="revision-action_rvy.php" server="104.196.232.125:2222" local="131329527580000000" remote="131329527580000000" Dst="2" />
<file name="agents_checklist_rvy.php" server="104.196.232.125:2222" local="131329527530000000" remote="131329527530000000" Dst="2" />
<file name="revisions.php" server="104.196.232.125:2222" local="131329527590000000" remote="131329527590000000" Dst="2" />
<file name="filters-admin-ui-item_rvy.php" server="104.196.232.125:2222" local="131329527530000000" remote="131329527530000000" Dst="2" />
<file name="revision-ui_rvy.php" server="104.196.232.125:2222" local="131329527590000000" remote="131329527590000000" Dst="2" />
<file name="revisionary.js" server="104.196.232.125:2222" local="131329527590000000" remote="131329527590000000" Dst="2" />
<file name="revisionary.css" server="104.196.232.125:2222" local="131329527590000000" remote="131329527590000000" Dst="2" />
<file name="super-edit-helper_rvy.php" server="104.196.232.125:2222" local="131329527600000000" remote="131329527600000000" Dst="2" />
<file name="revision-edit.js" server="104.196.232.125:2222" local="131329527590000000" remote="131329527590000000" Dst="2" />
<file name="about.php" server="104.196.232.125:2222" local="131329527520000000" remote="131329527520000000" Dst="2" />
<file name="admin-dashboard_rvy.php" server="104.196.232.125:2222" local="131329527520000000" remote="131329527520000000" Dst="2" />
<file name="options.php" server="104.196.232.125:2222" local="131329527580000000" remote="131329527580000000" Dst="2" />
<file name="revisionary-extra.js" server="104.196.232.125:2222" local="131329527590000000" remote="131329527590000000" Dst="2" />
<file name="admin-init_rvy.php" server="104.196.232.125:2222" local="131329527520000000" remote="131329527520000000" Dst="2" />
<file name="admin_rvy.php" server="104.196.232.125:2222" local="131329527530000000" remote="131329527530000000" Dst="2" />
<file name="admin_lib-mu_rvy.php" server="104.196.232.125:2222" local="131329527520000000" remote="131329527520000000" Dst="2" />
<file name="post-edit.js" server="104.196.232.125:2222" local="131329527580000000" remote="131329527580000000" Dst="2" />
</dwsync>